mozterm/__init__.py
mozterm/terminal.py
mozterm/widgets.py
mozterm-0.1.0.dist-info/DESCRIPTION.rst
mozterm-0.1.0.dist-info/METADATA
mozterm-0.1.0.dist-info/RECORD
mozterm-0.1.0.dist-info/WHEEL
mozterm-0.1.0.dist-info/metadata.json
mozterm-0.1.0.dist-info/top_level.txt
