Metadata-Version: 2.0
Name: mozterm
Version: 0.1.0
Summary: Terminal abstractions built around the blessings module.
Home-page: UNKNOWN
Author: Andrew Halberstadt
Author-email: ahalberstadt@mozilla.com
License: MPL 2.0
Platform: UNKNOWN
Classifier: Environment :: Console
Classifier: Development Status :: 3 - Alpha
Classifier: License :: OSI Approved :: Mozilla Public License 2.0 (MPL 2.0)
Classifier: Natural Language :: English
